metasub_utils.bridges-0.2.0-py3.6-nspkg.pth
metasub_utils/bridges/__init__.py
metasub_utils/bridges/bridges.py
metasub_utils/bridges/cli.py
metasub_utils/bridges/constants.py
metasub_utils/bridges/utils.py
metasub_utils.bridges-0.2.0.dist-info/METADATA
metasub_utils.bridges-0.2.0.dist-info/RECORD
metasub_utils.bridges-0.2.0.dist-info/WHEEL
metasub_utils.bridges-0.2.0.dist-info/namespace_packages.txt
metasub_utils.bridges-0.2.0.dist-info/top_level.txt
